wizarddocx/__init__.py
wizarddocx/wizard_extract.py
wizarddocx/utils/__init__.py
wizarddocx/utils/errors/__init__.py
wizarddocx/utils/errors/errors.py
wizarddocx/utils/errors/errors_handle.py
wizarddocx/wizard_docx/__init__.py
wizarddocx/wizard_docx/extraction_text.py
wizarddocx/wizard_docx/tool/__init__.py
wizarddocx/wizard_docx/tool/doc_reader.py
wizarddocx/wizard_docx/tool/docx_reader.py
wizarddocx/wizard_docx/utils/__init__.py
wizarddocx/wizard_docx/utils/selector.py
wizarddocx-1.0.0.dist-info/licenses/LICENSE
wizarddocx-1.0.0.dist-info/METADATA
wizarddocx-1.0.0.dist-info/WHEEL
wizarddocx-1.0.0.dist-info/top_level.txt
wizarddocx-1.0.0.dist-info/RECORD
