Metadata-Version: 2.4
Name: wizarddocx
Version: 1.0.0
Summary: Text extraction from Microsoft Word files. Parses Word documents natively and can optionally run local OCR with Tesseract for embedded images or scanned pages. Supports page selection and bytes input. Legacy .doc is read-only and OCR is not available.
Author-email: Mattia Rubino <textwizard.dev@gmail.com>
License: WizardDocx — Copyright (C) 2024–2025 Mattia Rubino
Project-URL: Homepage, https://github.com/textwizard-dev/wizarddocx
Project-URL: Source, https://github.com/textwizard-dev/wizarddocx
Project-URL: Documentation, https://wizarddocx.readthedocs.io/en/latest/
Keywords: docx,microsoft-word,word,text-extraction,document-processing,ocr,tesseract,doc
Classifier: Programming Language :: Python :: 3
Classifier: Programming Language :: Python :: 3.9
Classifier: Programming Language :: Python :: 3.10
Classifier: Programming Language :: Python :: 3.11
Classifier: Intended Audience :: Developers
Classifier: Topic :: Text Processing
Classifier: License :: OSI Approved :: GNU Affero General Public License v3 or later (AGPLv3+)
Requires-Python: >=3.9
License-File: LICENSE
Requires-Dist: pip>=2.3.1
Requires-Dist: pytesseract>=0.3.13
Dynamic: license-file
